fluent_validator/__init__.py
fluent_validator/validator.py
fluent_validator/validators/__init__.py
fluent_validator/validators/base_validator.py
fluent_validator/validators/type_validator.py
fluent_validator/validators/value_validator.py
fluent_validator-0.1.0.dist-info/LICENSE
fluent_validator-0.1.0.dist-info/METADATA
fluent_validator-0.1.0.dist-info/WHEEL
fluent_validator-0.1.0.dist-info/top_level.txt
fluent_validator-0.1.0.dist-info/RECORD
