Metadata-Version: 2.1
Name: fluent_validator
Version: 0.1.0
Summary: Package to validate data in a fluent way
Home-page: https://github.com/mariotaddeucci/fluent_validator
Author: Mario Taddeuci
Author-email: mariotaddeucci@gmx.com
Keywords: validator,check,fluent,assert
Classifier: Development Status :: 1 - Planning
Classifier: Intended Audience :: Developers
Classifier: Programming Language :: Python :: 3
Classifier: Operating System :: Unix
Classifier: Operating System :: MacOS :: MacOS X
Classifier: Operating System :: Microsoft :: Windows
License-File: LICENSE
